nlpatl/__init__.py
nlpatl/dataset/__init__.py
nlpatl/dataset/dataset.py
nlpatl/learning/__init__.py
nlpatl/learning/learning.py
nlpatl/learning/mismatch_farthest_learning.py
nlpatl/learning/semi_supervised_learning.py
nlpatl/learning/supervised_learning.py
nlpatl/learning/unsupervised_learning.py
nlpatl/models/__init__.py
nlpatl/models/classification/__init__.py
nlpatl/models/classification/classification.py
nlpatl/models/classification/sklearn_classification.py
nlpatl/models/classification/xgboost_classification.py
nlpatl/models/clustering/__init__.py
nlpatl/models/clustering/clustering.py
nlpatl/models/clustering/sklearn_clustering.py
nlpatl/models/embeddings/__init__.py
nlpatl/models/embeddings/embeddings.py
nlpatl/models/embeddings/sentence_transformers.py
nlpatl/models/embeddings/torchvision.py
nlpatl/models/embeddings/transformers.py
nlpatl/sampling/__init__.py
nlpatl/sampling/sampling.py
nlpatl/sampling/certainty/__init__.py
nlpatl/sampling/certainty/most_confidence.py
nlpatl/sampling/clustering/__init__.py
nlpatl/sampling/clustering/farthest.py
nlpatl/sampling/clustering/nearest_mean.py
nlpatl/sampling/uncertainty/__init__.py
nlpatl/sampling/uncertainty/entropy.py
nlpatl/sampling/uncertainty/least_confidence.py
nlpatl/sampling/uncertainty/margin.py
nlpatl/sampling/uncertainty/mismatch.py
nlpatl-0.0.2.dist-info/LICENSE
nlpatl-0.0.2.dist-info/METADATA
nlpatl-0.0.2.dist-info/WHEEL
nlpatl-0.0.2.dist-info/top_level.txt
nlpatl-0.0.2.dist-info/RECORD
