Metadata-Version: 2.1
Name: nlpatl
Version: 0.0.2
Summary: Natural language processing active learning library for deep neural networks
Home-page: https://github.com/makcedward/nlpatl
Author: Edward Ma
Author-email: makcedward@gmail.com
License: MIT
Keywords: deep learning,neural network,machine learning,nlp,natural language processing,text,active learning,data labeling,ai,ml
Platform: UNKNOWN
License-File: LICENSE
Requires-Dist: scipy (>=1.7.0)
Requires-Dist: numpy (>=1.16.2)
Requires-Dist: scikit-learn (>=1.0.1)
Requires-Dist: transformers (>=4.11.3)
Provides-Extra: all
Requires-Dist: scipy ; extra == 'all'
Requires-Dist: numpy ; extra == 'all'
Requires-Dist: transformers ; extra == 'all'
Requires-Dist: scikit-learn ; extra == 'all'
Requires-Dist: xgboost ; extra == 'all'
Requires-Dist: datasets ; extra == 'all'
Requires-Dist: torch ; extra == 'all'
Requires-Dist: torchvision ; extra == 'all'
Requires-Dist: torchaudio ; extra == 'all'
Requires-Dist: tensorflow ; extra == 'all'
Requires-Dist: Pillow ; extra == 'all'
Requires-Dist: sphinx-rtd-theme ; extra == 'all'
Requires-Dist: sentence-transformers ; extra == 'all'
Provides-Extra: image
Requires-Dist: Pillow (>=8.2.0) ; extra == 'image'
Provides-Extra: text
Requires-Dist: transformers (>=4.11.3) ; extra == 'text'
Requires-Dist: sentence-transformers (>=2.1.0) ; extra == 'text'
